promptlang/__init__.py
promptlang/promptlang.py
PromptLang-0.1.0.dist-info/METADATA
PromptLang-0.1.0.dist-info/WHEEL
PromptLang-0.1.0.dist-info/top_level.txt
PromptLang-0.1.0.dist-info/RECORD
