Metadata-Version: 2.2
Name: PromptLang
Version: 0.1.0
Summary: A lightweight language for dynamic prompt processing with inline data transformations and caching.
Home-page: https://github.com/injemamul/PromptLang
Author: Md Injemamul Irshad
Author-email: injemam.irshad@gmail.com
License: MIT
Classifier: Programming Language :: Python :: 3
Classifier: License :: OSI Approved :: MIT License
Classifier: Operating System :: OS Independent
Requires-Python: >=3.6
Dynamic: author
Dynamic: author-email
Dynamic: classifier
Dynamic: description
Dynamic: description-content-type
Dynamic: home-page
Dynamic: license
Dynamic: requires-python
Dynamic: summary
